pygolomb/__init__.py
pygolomb/golomb.py
pygolomb-0.1.1.dist-info/COPYING
pygolomb-0.1.1.dist-info/METADATA
pygolomb-0.1.1.dist-info/WHEEL
pygolomb-0.1.1.dist-info/RECORD
