Metadata-Version: 2.1
Name: pygolomb
Version: 0.1.1
Summary: A small Python library to test binary sequences with Golomb's randomness postulates.
Author: alxwnth
Author-email: alxwnth@posteo.me
Requires-Python: >=3.12,<4.0
Classifier: Programming Language :: Python :: 3
Classifier: Programming Language :: Python :: 3.12
